<?xml version="1.0" encoding="utf-8" ?>
<!--
  ~ Copyright (c) 2024 NSTDA
  -->
<templates>
    <t t-name="ni_observation.sectionAndNoteListRenderer" t-inherit="web.ListRenderer" t-inherit-mode="primary" owl="1">
        <xpath expr="//table" position="attributes">
            <attribute name="class" position="add" separator=" ">o_section_and_note_list_view</attribute>
        </xpath>
    </t>
    <t t-name="ni_observation.SectionAndNoteText" owl="1">
        <t t-component="componentToUse" t-props="props" />
    </t>
</templates>
